{
  "metadata": {
    "subject": "Geography",
    "year": "KS2",
    "source_file": "Geography_KS2_extracted.json",
    "term_count": 70
  },
  "terms": [
    {
      "term_id": "VOC-GE-adaptation",
      "term": "adaptation",
      "definition": "A feature or behaviour that helps a living thing survive in its environment.",
      "subject": "Geography",
      "word_class": "noun",
      "tier": 3,
      "etymology": "From Latin adaptare, to fit",
      "example_usage": "Cacti have adaptations like thick stems to store water in the desert.",
      "common_errors": "Thinking adaptation is a conscious choice",
      "related_everyday_word": "adjustment",
      "concept_links": [
        {
          "concept_id": "GE-KS2-C002",
          "introduced": true,
          "importance": "core"
        },
        {
          "concept_id": "GE-KS3-C003",
          "introduced": false,
          "importance": "core"
        },
        {
          "concept_id": "GE-KS4-C002",
          "introduced": false,
          "importance": "core"
        },
        {
          "concept_id": "GE-KS4-C015",
          "introduced": false,
          "importance": "core"
        }
      ]
    },
    {
      "term_id": "VOC-GE-americas",
      "term": "americas",
      "definition": "The continents of North America and South America considered together.",
      "subject": "Geography",
      "word_class": "noun",
      "tier": 3,
      "etymology": "Named after Amerigo Vespucci",
      "example_usage": "The Americas stretch from the Arctic in the north to the tip of South America.",
      "common_errors": "",
      "related_everyday_word": "",
      "concept_links": [
        {
          "concept_id": "GE-KS2-C006",
          "introduced": true,
          "importance": "core"
        }
      ]
    },
    {
      "term_id": "VOC-GE-antarctic",
      "term": "antarctic",
      "definition": "Relating to the region around the South Pole, characterised by extreme cold and ice.",
      "subject": "Geography",
      "word_class": "adjective",
      "tier": 3,
      "etymology": "From Greek antarktikos",
      "example_usage": "The Antarctic climate zone is the coldest on Earth.",
      "common_errors": "Confusing Antarctic with Arctic",
      "related_everyday_word": "",
      "concept_links": [
        {
          "concept_id": "GE-KS2-C001",
          "introduced": true,
          "importance": "core"
        }
      ]
    },
    {
      "term_id": "VOC-GE-biome",
      "term": "biome",
      "definition": "A large naturally occurring community of plants and animals adapted to a particular climate, such as desert or rainforest.",
      "subject": "Geography",
      "word_class": "noun",
      "tier": 3,
      "etymology": "From Greek bios, life",
      "example_usage": "The tropical rainforest biome receives high rainfall and has great biodiversity.",
      "common_errors": "Confusing biome with ecosystem; biomes are larger",
      "related_everyday_word": "habitat type",
      "concept_links": [
        {
          "concept_id": "GE-KS2-C002",
          "introduced": true,
          "importance": "core"
        }
      ]
    },
    {
      "term_id": "VOC-GE-characteristic",
      "term": "characteristic",
      "definition": "A typical or distinguishing quality or feature of a place or environment.",
      "subject": "Geography",
      "word_class": "noun",
      "tier": 3,
      "etymology": "From Greek kharakter",
      "example_usage": "One characteristic of a desert is very low rainfall.",
      "common_errors": "",
      "related_everyday_word": "feature",
      "concept_links": [
        {
          "concept_id": "GE-KS2-C006",
          "introduced": true,
          "importance": "core"
        }
      ]
    },
    {
      "term_id": "VOC-GE-climate-zone",
      "term": "climate zone",
      "definition": "A region of the world with a particular pattern of weather conditions, determined by latitude and other factors.",
      "subject": "Geography",
      "word_class": "phrase",
      "tier": 3,
      "etymology": "",
      "example_usage": "The UK is in the temperate climate zone, with mild weather.",
      "common_errors": "",
      "related_everyday_word": "",
      "concept_links": [
        {
          "concept_id": "GE-KS2-C002",
          "introduced": true,
          "importance": "core"
        }
      ]
    },
    {
      "term_id": "VOC-GE-condensation",
      "term": "condensation",
      "definition": "The process by which water vapour in the air cools and turns back into liquid water droplets, forming clouds.",
      "subject": "Geography",
      "word_class": "noun",
      "tier": 3,
      "etymology": "From Latin condensare, to make thick",
      "example_usage": "Condensation is the stage of the water cycle where clouds form.",
      "common_errors": "Confusing condensation with evaporation",
      "related_everyday_word": "",
      "concept_links": [
        {
          "concept_id": "GE-KS2-C003",
          "introduced": true,
          "importance": "core"
        }
      ]
    },
    {
      "term_id": "VOC-GE-contour",
      "term": "contour",
      "definition": "A line on a map joining points of equal height above sea level, showing the shape and steepness of the land.",
      "subject": "Geography",
      "word_class": "noun",
      "tier": 3,
      "etymology": "From Italian contorno, outline",
      "example_usage": "Closely spaced contour lines on a map indicate steep terrain.",
      "common_errors": "",
      "related_everyday_word": "height line",
      "concept_links": [
        {
          "concept_id": "GE-KS2-C005",
          "introduced": true,
          "importance": "core"
        },
        {
          "concept_id": "GE-KS3-C007",
          "introduced": false,
          "importance": "core"
        },
        {
          "concept_id": "GE-KS4-C009",
          "introduced": false,
          "importance": "core"
        }
      ]
    },
    {
      "term_id": "VOC-GE-conurbation",
      "term": "conurbation",
      "definition": "A large urban area formed when several towns or cities have grown together.",
      "subject": "Geography",
      "word_class": "noun",
      "tier": 3,
      "etymology": "From Latin con- (together) + urbs (city)",
      "example_usage": "Greater Manchester is a conurbation made up of several towns and cities.",
      "common_errors": "",
      "related_everyday_word": "sprawl",
      "concept_links": [
        {
          "concept_id": "GE-KS2-C004",
          "introduced": true,
          "importance": "core"
        }
      ]
    },
    {
      "term_id": "VOC-GE-coordinate",
      "term": "coordinate",
      "definition": "A pair of numbers used to specify the exact position of a point on a map using a grid reference system.",
      "subject": "Geography",
      "word_class": "noun",
      "tier": 3,
      "etymology": "From Latin coordinare, to arrange together",
      "example_usage": "The coordinates 52N, 1W tell us the exact location on the map.",
      "common_errors": "Confusing with the verb to coordinate",
      "related_everyday_word": "grid reference",
      "concept_links": [
        {
          "concept_id": "GE-KS2-C001",
          "introduced": true,
          "importance": "core"
        }
      ]
    },
    {
      "term_id": "VOC-GE-cultural",
      "term": "cultural",
      "definition": "Relating to the beliefs, customs, arts, and way of life of a particular group of people.",
      "subject": "Geography",
      "word_class": "adjective",
      "tier": 3,
      "etymology": "From Latin cultura, cultivation",
      "example_usage": "Cultural differences between countries include language, food, and traditions.",
      "common_errors": "",
      "related_everyday_word": "",
      "concept_links": [
        {
          "concept_id": "GE-KS2-C006",
          "introduced": true,
          "importance": "core"
        }
      ]
    },
    {
      "term_id": "VOC-GE-degree",
      "term": "degree",
      "definition": "A unit of measurement for angles, latitude, and longitude, shown by the symbol.",
      "subject": "Geography",
      "word_class": "noun",
      "tier": 3,
      "etymology": "From Latin gradus, step",
      "example_usage": "The equator is at zero degrees latitude.",
      "common_errors": "Confusing with temperature degrees or academic degrees",
      "related_everyday_word": "",
      "concept_links": [
        {
          "concept_id": "GE-KS2-C001",
          "introduced": true,
          "importance": "core"
        }
      ]
    },
    {
      "term_id": "VOC-GE-deposition",
      "term": "deposition",
      "definition": "The laying down of material such as sand, silt, or pebbles that has been carried by water, wind, or ice.",
      "subject": "Geography",
      "word_class": "noun",
      "tier": 3,
      "etymology": "From Latin deponere, to put down",
      "example_usage": "Deposition at the mouth of a river can form a delta.",
      "common_errors": "Confusing deposition with erosion",
      "related_everyday_word": "dropping",
      "concept_links": [
        {
          "concept_id": "GE-KS2-C003",
          "introduced": true,
          "importance": "core"
        },
        {
          "concept_id": "GE-KS4-C003",
          "introduced": false,
          "importance": "core"
        }
      ]
    },
    {
      "term_id": "VOC-GE-desert",
      "term": "desert",
      "definition": "A dry area of land that receives very little rainfall, often with extreme temperatures.",
      "subject": "Geography",
      "word_class": "noun",
      "tier": 3,
      "etymology": "From Latin desertum, abandoned place",
      "example_usage": "The Sahara is the worlds largest hot desert.",
      "common_errors": "Thinking all deserts are hot; some are cold",
      "related_everyday_word": "",
      "concept_links": [
        {
          "concept_id": "GE-KS2-C002",
          "introduced": true,
          "importance": "core"
        },
        {
          "concept_id": "GE-KS3-C005",
          "introduced": false,
          "importance": "core"
        }
      ]
    },
    {
      "term_id": "VOC-GE-distribution",
      "term": "distribution",
      "definition": "The way in which something is spread out or arranged across an area.",
      "subject": "Geography",
      "word_class": "noun",
      "tier": 3,
      "etymology": "From Latin distribuere, to divide",
      "example_usage": "The distribution of rainfall across the UK is uneven, with more in the west.",
      "common_errors": "",
      "related_everyday_word": "spread",
      "concept_links": [
        {
          "concept_id": "GE-KS2-C004",
          "introduced": true,
          "importance": "core"
        },
        {
          "concept_id": "GE-KS3-C004",
          "introduced": false,
          "importance": "core"
        },
        {
          "concept_id": "GE-KS3-C005",
          "introduced": false,
          "importance": "core"
        }
      ]
    },
    {
      "term_id": "VOC-GE-drainage-basin",
      "term": "drainage basin",
      "definition": "The area of land where all the water drains into one particular river system.",
      "subject": "Geography",
      "word_class": "phrase",
      "tier": 3,
      "etymology": "",
      "example_usage": "The drainage basin of the River Thames covers a large area of southern England.",
      "common_errors": "",
      "related_everyday_word": "catchment area",
      "concept_links": [
        {
          "concept_id": "GE-KS2-C003",
          "introduced": true,
          "importance": "core"
        }
      ]
    },
    {
      "term_id": "VOC-GE-easting",
      "term": "easting",
      "definition": "The first part of a grid reference, reading left to right along the bottom of a map.",
      "subject": "Geography",
      "word_class": "noun",
      "tier": 3,
      "etymology": "From east + -ing",
      "example_usage": "Always read the easting before the northing when giving a grid reference.",
      "common_errors": "Getting easting and northing the wrong way round",
      "related_everyday_word": "",
      "concept_links": [
        {
          "concept_id": "GE-KS2-C005",
          "introduced": true,
          "importance": "core"
        },
        {
          "concept_id": "GE-KS4-C009",
          "introduced": false,
          "importance": "core"
        }
      ]
    },
    {
      "term_id": "VOC-GE-economic-activity",
      "term": "economic activity",
      "definition": "Work and industry that produces goods or services, contributing to the wealth of a region or country.",
      "subject": "Geography",
      "word_class": "phrase",
      "tier": 3,
      "etymology": "",
      "example_usage": "Farming, manufacturing, and tourism are all types of economic activity.",
      "common_errors": "",
      "related_everyday_word": "business",
      "concept_links": [
        {
          "concept_id": "GE-KS2-C006",
          "introduced": true,
          "importance": "core"
        }
      ]
    },
    {
      "term_id": "VOC-GE-ecosystem",
      "term": "ecosystem",
      "definition": "A community of living things and their physical environment, interacting as a system.",
      "subject": "Geography",
      "word_class": "noun",
      "tier": 3,
      "etymology": "From Greek oikos (house) + systema",
      "example_usage": "A pond is a small ecosystem where plants, insects, and fish all depend on each other.",
      "common_errors": "Confusing ecosystem with habitat",
      "related_everyday_word": "",
      "concept_links": [
        {
          "concept_id": "GE-KS2-C002",
          "introduced": true,
          "importance": "core"
        },
        {
          "concept_id": "GE-KS4-C015",
          "introduced": false,
          "importance": "core"
        }
      ]
    },
    {
      "term_id": "VOC-GE-elevation",
      "term": "elevation",
      "definition": "The height of a point above sea level, often shown by contour lines on a map.",
      "subject": "Geography",
      "word_class": "noun",
      "tier": 3,
      "etymology": "From Latin elevare, to raise",
      "example_usage": "The elevation of the mountain peak is 1,345 metres above sea level.",
      "common_errors": "",
      "related_everyday_word": "height",
      "concept_links": [
        {
          "concept_id": "GE-KS2-C005",
          "introduced": true,
          "importance": "core"
        }
      ]
    },
    {
      "term_id": "VOC-GE-energy",
      "term": "energy",
      "definition": "The power used to run machines, heat buildings, and provide light, derived from various sources.",
      "subject": "Geography",
      "word_class": "noun",
      "tier": 3,
      "etymology": "From Greek energeia, activity",
      "example_usage": "Wind turbines convert wind energy into electricity.",
      "common_errors": "",
      "related_everyday_word": "power",
      "concept_links": [
        {
          "concept_id": "GE-KS2-C004",
          "introduced": true,
          "importance": "core"
        }
      ]
    },
    {
      "term_id": "VOC-GE-erosion",
      "term": "erosion",
      "definition": "The wearing away and removal of rock, soil, or land surface by water, wind, ice, or gravity.",
      "subject": "Geography",
      "word_class": "noun",
      "tier": 3,
      "etymology": "From Latin erodere, to eat away",
      "example_usage": "Erosion by the sea has created the cliffs along the coast.",
      "common_errors": "Confusing erosion with weathering, which breaks rock without moving it",
      "related_everyday_word": "wearing away",
      "concept_links": [
        {
          "concept_id": "GE-KS2-C003",
          "introduced": true,
          "importance": "core"
        }
      ]
    },
    {
      "term_id": "VOC-GE-european",
      "term": "european",
      "definition": "Relating to the continent of Europe, its countries, or its peoples.",
      "subject": "Geography",
      "word_class": "adjective",
      "tier": 3,
      "etymology": "From Greek Europe",
      "example_usage": "France and Germany are European countries close to the United Kingdom.",
      "common_errors": "",
      "related_everyday_word": "",
      "concept_links": [
        {
          "concept_id": "GE-KS2-C006",
          "introduced": true,
          "importance": "core"
        }
      ]
    },
    {
      "term_id": "VOC-GE-evaporation",
      "term": "evaporation",
      "definition": "The process by which liquid water is heated and turns into water vapour, rising into the atmosphere.",
      "subject": "Geography",
      "word_class": "noun",
      "tier": 3,
      "etymology": "From Latin evaporare, to turn to vapour",
      "example_usage": "Evaporation from the sea is the first stage of the water cycle.",
      "common_errors": "Confusing evaporation with condensation",
      "related_everyday_word": "drying up",
      "concept_links": [
        {
          "concept_id": "GE-KS2-C003",
          "introduced": true,
          "importance": "core"
        }
      ]
    },
    {
      "term_id": "VOC-GE-export",
      "term": "export",
      "definition": "Goods or services sold and sent to another country.",
      "subject": "Geography",
      "word_class": "noun",
      "tier": 3,
      "etymology": "From Latin exportare, to carry out",
      "example_usage": "Oil is a major export of countries in the Middle East.",
      "common_errors": "Confusing export (sending out) with import (bringing in)",
      "related_everyday_word": "selling abroad",
      "concept_links": [
        {
          "concept_id": "GE-KS2-C004",
          "introduced": true,
          "importance": "core"
        }
      ]
    },
    {
      "term_id": "VOC-GE-flood-plain",
      "term": "flood plain",
      "definition": "A flat area of land on either side of a river that is prone to flooding when the river overflows.",
      "subject": "Geography",
      "word_class": "phrase",
      "tier": 3,
      "etymology": "",
      "example_usage": "The flood plain is very fertile because of the silt deposited by floods.",
      "common_errors": "",
      "related_everyday_word": "river flat",
      "concept_links": [
        {
          "concept_id": "GE-KS2-C003",
          "introduced": true,
          "importance": "core"
        }
      ]
    },
    {
      "term_id": "VOC-GE-four-figure",
      "term": "four-figure",
      "definition": "A grid reference using four numbers to locate a square on a map.",
      "subject": "Geography",
      "word_class": "adjective",
      "tier": 3,
      "etymology": "",
      "example_usage": "The four-figure grid reference 2347 tells us which square the church is in.",
      "common_errors": "",
      "related_everyday_word": "",
      "concept_links": [
        {
          "concept_id": "GE-KS2-C005",
          "introduced": true,
          "importance": "core"
        }
      ]
    },
    {
      "term_id": "VOC-GE-grid-reference",
      "term": "grid reference",
      "definition": "A set of numbers used to identify a precise location on an Ordnance Survey or similar map.",
      "subject": "Geography",
      "word_class": "phrase",
      "tier": 3,
      "etymology": "",
      "example_usage": "We used a six-figure grid reference to find the exact location of the bridge.",
      "common_errors": "Reading eastings and northings in the wrong order",
      "related_everyday_word": "map coordinates",
      "concept_links": [
        {
          "concept_id": "GE-KS2-C005",
          "introduced": true,
          "importance": "core"
        },
        {
          "concept_id": "GE-KS3-C007",
          "introduced": false,
          "importance": "core"
        },
        {
          "concept_id": "GE-KS4-C009",
          "introduced": false,
          "importance": "core"
        }
      ]
    },
    {
      "term_id": "VOC-GE-hamlet",
      "term": "hamlet",
      "definition": "A very small settlement, smaller than a village, typically without a church or shops.",
      "subject": "Geography",
      "word_class": "noun",
      "tier": 3,
      "etymology": "From Old French hamelet, small village",
      "example_usage": "A hamlet is the smallest type of settlement and may have only a few houses.",
      "common_errors": "",
      "related_everyday_word": "tiny village",
      "concept_links": [
        {
          "concept_id": "GE-KS2-C004",
          "introduced": true,
          "importance": "core"
        }
      ]
    },
    {
      "term_id": "VOC-GE-hemisphere",
      "term": "hemisphere",
      "definition": "One half of the Earth, divided either into Northern/Southern (by the equator) or Eastern/Western (by the Prime Meridian).",
      "subject": "Geography",
      "word_class": "noun",
      "tier": 3,
      "etymology": "From Greek hemi (half) + sphaira (sphere)",
      "example_usage": "The United Kingdom is in the Northern Hemisphere.",
      "common_errors": "",
      "related_everyday_word": "half of Earth",
      "concept_links": [
        {
          "concept_id": "GE-KS2-C001",
          "introduced": true,
          "importance": "core"
        }
      ]
    },
    {
      "term_id": "VOC-GE-human-geography",
      "term": "human geography",
      "definition": "The study of how people interact with their environment, including settlement, industry, and population.",
      "subject": "Geography",
      "word_class": "phrase",
      "tier": 3,
      "etymology": "",
      "example_usage": "Human geography looks at where people live and how they use the land.",
      "common_errors": "Confusing human geography with physical geography",
      "related_everyday_word": "people geography",
      "concept_links": [
        {
          "concept_id": "GE-KS2-C006",
          "introduced": true,
          "importance": "core"
        },
        {
          "concept_id": "GE-KS3-C006",
          "introduced": false,
          "importance": "core"
        }
      ]
    },
    {
      "term_id": "VOC-GE-import",
      "term": "import",
      "definition": "Goods or services bought from another country and brought in.",
      "subject": "Geography",
      "word_class": "noun",
      "tier": 3,
      "etymology": "From Latin importare, to bring in",
      "example_usage": "The UK imports bananas because they cannot grow in its climate.",
      "common_errors": "Confusing import with export",
      "related_everyday_word": "buying from abroad",
      "concept_links": [
        {
          "concept_id": "GE-KS2-C004",
          "introduced": true,
          "importance": "core"
        }
      ]
    },
    {
      "term_id": "VOC-GE-infiltration",
      "term": "infiltration",
      "definition": "The process by which rainwater soaks into the soil and underlying rock.",
      "subject": "Geography",
      "word_class": "noun",
      "tier": 3,
      "etymology": "From Latin in + filtrare, to strain through",
      "example_usage": "After rain, infiltration moves water from the surface down into the ground.",
      "common_errors": "Confusing with the security meaning of infiltration",
      "related_everyday_word": "soaking in",
      "concept_links": [
        {
          "concept_id": "GE-KS2-C003",
          "introduced": true,
          "importance": "core"
        }
      ]
    },
    {
      "term_id": "VOC-GE-longitude",
      "term": "longitude",
      "definition": "Imaginary vertical lines on a map or globe measuring distance east or west of the Prime Meridian.",
      "subject": "Geography",
      "word_class": "noun",
      "tier": 3,
      "etymology": "From Latin longitudo, length",
      "example_usage": "Lines of longitude run from the North Pole to the South Pole.",
      "common_errors": "Confusing longitude (vertical) with latitude (horizontal)",
      "related_everyday_word": "",
      "concept_links": [
        {
          "concept_id": "GE-KS2-C001",
          "introduced": true,
          "importance": "core"
        },
        {
          "concept_id": "GE-KS4-C009",
          "introduced": false,
          "importance": "core"
        }
      ]
    },
    {
      "term_id": "VOC-GE-meander",
      "term": "meander",
      "definition": "A winding curve or bend in a river, typically found in the middle and lower course.",
      "subject": "Geography",
      "word_class": "noun",
      "tier": 3,
      "etymology": "From the River Meander in Turkey, famous for its winding path",
      "example_usage": "The river has formed large meanders as it flows across the flat flood plain.",
      "common_errors": "",
      "related_everyday_word": "bend",
      "concept_links": [
        {
          "concept_id": "GE-KS2-C003",
          "introduced": true,
          "importance": "core"
        },
        {
          "concept_id": "GE-KS4-C003",
          "introduced": false,
          "importance": "core"
        }
      ]
    },
    {
      "term_id": "VOC-GE-meridian",
      "term": "meridian",
      "definition": "A line of longitude; the Prime Meridian at Greenwich is the reference point at 0 degrees.",
      "subject": "Geography",
      "word_class": "noun",
      "tier": 3,
      "etymology": "From Latin meridianus, of midday",
      "example_usage": "The Prime Meridian passes through Greenwich in London.",
      "common_errors": "",
      "related_everyday_word": "",
      "concept_links": [
        {
          "concept_id": "GE-KS2-C001",
          "introduced": true,
          "importance": "core"
        }
      ]
    },
    {
      "term_id": "VOC-GE-mineral",
      "term": "mineral",
      "definition": "A naturally occurring substance found in rocks and soil, often extracted for human use.",
      "subject": "Geography",
      "word_class": "noun",
      "tier": 3,
      "etymology": "From Medieval Latin minerale",
      "example_usage": "Iron ore is a mineral that has been mined for thousands of years.",
      "common_errors": "",
      "related_everyday_word": "",
      "concept_links": [
        {
          "concept_id": "GE-KS2-C004",
          "introduced": true,
          "importance": "core"
        }
      ]
    },
    {
      "term_id": "VOC-GE-mouth",
      "term": "mouth",
      "definition": "The point where a river flows into the sea, a lake, or another river.",
      "subject": "Geography",
      "word_class": "noun",
      "tier": 3,
      "etymology": "From Old English mutha",
      "example_usage": "The mouth of the River Thames is where it flows into the North Sea.",
      "common_errors": "Confusing with the body part",
      "related_everyday_word": "",
      "concept_links": [
        {
          "concept_id": "GE-KS2-C003",
          "introduced": true,
          "importance": "core"
        }
      ]
    },
    {
      "term_id": "VOC-GE-national-grid",
      "term": "national grid",
      "definition": "The system of numbered grid lines covering Ordnance Survey maps of the United Kingdom.",
      "subject": "Geography",
      "word_class": "phrase",
      "tier": 3,
      "etymology": "",
      "example_usage": "The National Grid allows us to give accurate grid references for any location in the UK.",
      "common_errors": "Confusing with the electricity National Grid",
      "related_everyday_word": "",
      "concept_links": [
        {
          "concept_id": "GE-KS2-C005",
          "introduced": true,
          "importance": "core"
        }
      ]
    },
    {
      "term_id": "VOC-GE-natural-resource",
      "term": "natural resource",
      "definition": "A material found in nature that is useful to people, such as water, wood, minerals, or soil.",
      "subject": "Geography",
      "word_class": "phrase",
      "tier": 3,
      "etymology": "",
      "example_usage": "Water is a natural resource that is essential for farming and drinking.",
      "common_errors": "",
      "related_everyday_word": "raw material",
      "concept_links": [
        {
          "concept_id": "GE-KS2-C004",
          "introduced": true,
          "importance": "core"
        }
      ]
    },
    {
      "term_id": "VOC-GE-northing",
      "term": "northing",
      "definition": "The second part of a grid reference, reading upwards from the bottom of a map.",
      "subject": "Geography",
      "word_class": "noun",
      "tier": 3,
      "etymology": "From north + -ing",
      "example_usage": "After finding the easting, read the northing to complete the grid reference.",
      "common_errors": "",
      "related_everyday_word": "",
      "concept_links": [
        {
          "concept_id": "GE-KS2-C005",
          "introduced": true,
          "importance": "core"
        },
        {
          "concept_id": "GE-KS4-C009",
          "introduced": false,
          "importance": "core"
        }
      ]
    },
    {
      "term_id": "VOC-GE-ordnance-survey",
      "term": "ordnance survey",
      "definition": "The national mapping agency of Great Britain, producing detailed topographic maps.",
      "subject": "Geography",
      "word_class": "phrase",
      "tier": 3,
      "etymology": "Originally created for military surveying",
      "example_usage": "Ordnance Survey maps show contour lines, footpaths, and buildings in great detail.",
      "common_errors": "",
      "related_everyday_word": "OS map",
      "concept_links": [
        {
          "concept_id": "GE-KS2-C005",
          "introduced": true,
          "importance": "core"
        },
        {
          "concept_id": "GE-KS3-C007",
          "introduced": false,
          "importance": "core"
        },
        {
          "concept_id": "GE-KS4-C009",
          "introduced": false,
          "importance": "core"
        }
      ]
    },
    {
      "term_id": "VOC-GE-parallel",
      "term": "parallel",
      "definition": "A line of latitude running east-west around the Earth, parallel to the equator.",
      "subject": "Geography",
      "word_class": "noun",
      "tier": 3,
      "etymology": "From Greek parallelos",
      "example_usage": "The Tropic of Cancer is a parallel at about 23.5 degrees north.",
      "common_errors": "",
      "related_everyday_word": "",
      "concept_links": [
        {
          "concept_id": "GE-KS2-C001",
          "introduced": true,
          "importance": "core"
        }
      ]
    },
    {
      "term_id": "VOC-GE-physical-geography",
      "term": "physical geography",
      "definition": "The study of natural features and processes on the Earths surface, including landforms, weather, and rivers.",
      "subject": "Geography",
      "word_class": "phrase",
      "tier": 3,
      "etymology": "",
      "example_usage": "Physical geography covers topics like rivers, mountains, and climate.",
      "common_errors": "Confusing with human geography",
      "related_everyday_word": "",
      "concept_links": [
        {
          "concept_id": "GE-KS2-C006",
          "introduced": true,
          "importance": "core"
        },
        {
          "concept_id": "GE-KS3-C006",
          "introduced": false,
          "importance": "core"
        }
      ]
    },
    {
      "term_id": "VOC-GE-polar",
      "term": "polar",
      "definition": "Relating to the areas around the North or South Pole, characterised by extreme cold.",
      "subject": "Geography",
      "word_class": "adjective",
      "tier": 3,
      "etymology": "From Latin polaris",
      "example_usage": "Polar regions have long winters with little or no sunlight.",
      "common_errors": "",
      "related_everyday_word": "",
      "concept_links": [
        {
          "concept_id": "GE-KS2-C002",
          "introduced": true,
          "importance": "core"
        }
      ]
    },
    {
      "term_id": "VOC-GE-precipitation",
      "term": "precipitation",
      "definition": "Water that falls from the atmosphere to the Earths surface as rain, snow, sleet, or hail.",
      "subject": "Geography",
      "word_class": "noun",
      "tier": 3,
      "etymology": "From Latin praecipitare, to fall headlong",
      "example_usage": "Precipitation is highest in the mountainous areas of western Britain.",
      "common_errors": "Thinking precipitation only means rain",
      "related_everyday_word": "rainfall",
      "concept_links": [
        {
          "concept_id": "GE-KS2-C002",
          "introduced": true,
          "importance": "core"
        },
        {
          "concept_id": "GE-KS2-C003",
          "introduced": false,
          "importance": "core"
        }
      ]
    },
    {
      "term_id": "VOC-GE-primary-sector",
      "term": "primary sector",
      "definition": "Economic activities that extract raw materials from the Earth, such as farming, fishing, and mining.",
      "subject": "Geography",
      "word_class": "phrase",
      "tier": 3,
      "etymology": "",
      "example_usage": "Farming is part of the primary sector because it produces food from the land.",
      "common_errors": "",
      "related_everyday_word": "",
      "concept_links": [
        {
          "concept_id": "GE-KS2-C004",
          "introduced": true,
          "importance": "core"
        }
      ]
    },
    {
      "term_id": "VOC-GE-prime-meridian",
      "term": "prime meridian",
      "definition": "The line of zero degrees longitude, passing through Greenwich in London, dividing the Earth into Eastern and Western Hemispheres.",
      "subject": "Geography",
      "word_class": "phrase",
      "tier": 3,
      "etymology": "From Latin primus (first) + meridianus",
      "example_usage": "The Prime Meridian at Greenwich is the starting point for measuring longitude.",
      "common_errors": "",
      "related_everyday_word": "",
      "concept_links": [
        {
          "concept_id": "GE-KS2-C001",
          "introduced": true,
          "importance": "core"
        }
      ]
    },
    {
      "term_id": "VOC-GE-rainforest",
      "term": "rainforest",
      "definition": "A dense forest found in tropical areas with high rainfall and warm temperatures year-round.",
      "subject": "Geography",
      "word_class": "noun",
      "tier": 3,
      "etymology": "From rain + forest",
      "example_usage": "The Amazon rainforest is the largest tropical rainforest in the world.",
      "common_errors": "Thinking all rainforests are tropical; temperate rainforests also exist",
      "related_everyday_word": "jungle",
      "concept_links": [
        {
          "concept_id": "GE-KS2-C002",
          "introduced": true,
          "importance": "core"
        }
      ]
    },
    {
      "term_id": "VOC-GE-region",
      "term": "region",
      "definition": "A large area of land that shares common features, such as climate, landscape, or culture.",
      "subject": "Geography",
      "word_class": "noun",
      "tier": 3,
      "etymology": "From Latin regio, direction",
      "example_usage": "The Lake District is a region known for its mountains and lakes.",
      "common_errors": "",
      "related_everyday_word": "area",
      "concept_links": [
        {
          "concept_id": "GE-KS2-C006",
          "introduced": true,
          "importance": "core"
        },
        {
          "concept_id": "GE-KS3-C005",
          "introduced": false,
          "importance": "core"
        },
        {
          "concept_id": "GE-KS3-C006",
          "introduced": false,
          "importance": "core"
        }
      ]
    },
    {
      "term_id": "VOC-GE-relief",
      "term": "relief",
      "definition": "The shape and height of the land surface, including hills, valleys, and plains.",
      "subject": "Geography",
      "word_class": "noun",
      "tier": 3,
      "etymology": "From Italian rilievo, raised work",
      "example_usage": "The relief of an area is shown by contour lines on a map.",
      "common_errors": "Confusing with the everyday meaning of relief (feeling better)",
      "related_everyday_word": "terrain",
      "concept_links": [
        {
          "concept_id": "GE-KS2-C005",
          "introduced": true,
          "importance": "core"
        },
        {
          "concept_id": "GE-KS4-C009",
          "introduced": false,
          "importance": "core"
        }
      ]
    },
    {
      "term_id": "VOC-GE-run-off",
      "term": "run-off",
      "definition": "Water that flows over the land surface into streams and rivers rather than soaking into the ground.",
      "subject": "Geography",
      "word_class": "noun",
      "tier": 3,
      "etymology": "From run + off",
      "example_usage": "Heavy rainfall on hard ground leads to increased run-off and can cause flooding.",
      "common_errors": "",
      "related_everyday_word": "surface water",
      "concept_links": [
        {
          "concept_id": "GE-KS2-C003",
          "introduced": true,
          "importance": "core"
        }
      ]
    },
    {
      "term_id": "VOC-GE-savannah",
      "term": "savannah",
      "definition": "A tropical grassland with scattered trees, found between tropical rainforest and desert biomes.",
      "subject": "Geography",
      "word_class": "noun",
      "tier": 3,
      "etymology": "From Spanish sabana, from Taino zabana",
      "example_usage": "The African savannah is home to animals like lions, elephants, and zebras.",
      "common_errors": "Spelling it savanna (American) vs savannah (British)",
      "related_everyday_word": "grassland",
      "concept_links": [
        {
          "concept_id": "GE-KS2-C002",
          "introduced": true,
          "importance": "core"
        },
        {
          "concept_id": "GE-KS3-C005",
          "introduced": false,
          "importance": "core"
        }
      ]
    },
    {
      "term_id": "VOC-GE-secondary-sector",
      "term": "secondary sector",
      "definition": "Economic activities that manufacture or process raw materials into finished products.",
      "subject": "Geography",
      "word_class": "phrase",
      "tier": 3,
      "etymology": "",
      "example_usage": "A car factory is part of the secondary sector because it turns raw materials into a product.",
      "common_errors": "",
      "related_everyday_word": "manufacturing",
      "concept_links": [
        {
          "concept_id": "GE-KS2-C004",
          "introduced": true,
          "importance": "core"
        }
      ]
    },
    {
      "term_id": "VOC-GE-six-figure",
      "term": "six-figure",
      "definition": "A grid reference using six numbers to locate a precise point on a map.",
      "subject": "Geography",
      "word_class": "adjective",
      "tier": 3,
      "etymology": "",
      "example_usage": "A six-figure grid reference like 234478 pinpoints an exact location within a grid square.",
      "common_errors": "",
      "related_everyday_word": "",
      "concept_links": [
        {
          "concept_id": "GE-KS2-C005",
          "introduced": true,
          "importance": "core"
        }
      ]
    },
    {
      "term_id": "VOC-GE-source",
      "term": "source",
      "definition": "The place where a river begins, usually in high ground such as a spring or bog.",
      "subject": "Geography",
      "word_class": "noun",
      "tier": 3,
      "etymology": "From Old French sourse",
      "example_usage": "The source of the River Thames is in the Cotswold Hills.",
      "common_errors": "Confusing with the history meaning of source (evidence)",
      "related_everyday_word": "starting point",
      "concept_links": [
        {
          "concept_id": "GE-KS2-C003",
          "introduced": true,
          "importance": "core"
        }
      ]
    },
    {
      "term_id": "VOC-GE-spot-height",
      "term": "spot height",
      "definition": "A point on a map with a number showing its exact height above sea level.",
      "subject": "Geography",
      "word_class": "phrase",
      "tier": 3,
      "etymology": "",
      "example_usage": "The spot height on the map showed the hilltop was 324 metres above sea level.",
      "common_errors": "",
      "related_everyday_word": "",
      "concept_links": [
        {
          "concept_id": "GE-KS2-C005",
          "introduced": true,
          "importance": "core"
        }
      ]
    },
    {
      "term_id": "VOC-GE-temperate",
      "term": "temperate",
      "definition": "Relating to a climate zone with mild temperatures, moderate rainfall, and four distinct seasons.",
      "subject": "Geography",
      "word_class": "adjective",
      "tier": 3,
      "etymology": "From Latin temperatus, moderate",
      "example_usage": "The United Kingdom has a temperate climate with warm summers and cool winters.",
      "common_errors": "",
      "related_everyday_word": "mild",
      "concept_links": [
        {
          "concept_id": "GE-KS2-C002",
          "introduced": true,
          "importance": "core"
        }
      ]
    },
    {
      "term_id": "VOC-GE-tertiary-sector",
      "term": "tertiary sector",
      "definition": "Economic activities that provide services rather than producing goods, such as shops, schools, and hospitals.",
      "subject": "Geography",
      "word_class": "phrase",
      "tier": 3,
      "etymology": "From Latin tertiarius, of the third",
      "example_usage": "Teaching and nursing are part of the tertiary sector.",
      "common_errors": "",
      "related_everyday_word": "service industry",
      "concept_links": [
        {
          "concept_id": "GE-KS2-C004",
          "introduced": true,
          "importance": "core"
        }
      ]
    },
    {
      "term_id": "VOC-GE-time-zone",
      "term": "time zone",
      "definition": "A region of the Earth that observes the same standard time, based on longitude.",
      "subject": "Geography",
      "word_class": "phrase",
      "tier": 3,
      "etymology": "",
      "example_usage": "The UK and France are in different time zones, so their clocks show different times.",
      "common_errors": "",
      "related_everyday_word": "",
      "concept_links": [
        {
          "concept_id": "GE-KS2-C001",
          "introduced": true,
          "importance": "core"
        }
      ]
    },
    {
      "term_id": "VOC-GE-topographic",
      "term": "topographic",
      "definition": "Relating to the detailed mapping of the physical features of an area, including contours and landmarks.",
      "subject": "Geography",
      "word_class": "adjective",
      "tier": 3,
      "etymology": "From Greek topos (place) + graphein (to write)",
      "example_usage": "A topographic map shows the height and shape of the land using contour lines.",
      "common_errors": "",
      "related_everyday_word": "",
      "concept_links": [
        {
          "concept_id": "GE-KS2-C005",
          "introduced": true,
          "importance": "core"
        },
        {
          "concept_id": "GE-KS3-C007",
          "introduced": false,
          "importance": "core"
        }
      ]
    },
    {
      "term_id": "VOC-GE-trade",
      "term": "trade",
      "definition": "The buying and selling of goods and services between people, regions, or countries.",
      "subject": "Geography",
      "word_class": "noun",
      "tier": 3,
      "etymology": "From Middle Low German trade",
      "example_usage": "International trade means countries can buy goods they cannot produce themselves.",
      "common_errors": "",
      "related_everyday_word": "business",
      "concept_links": [
        {
          "concept_id": "GE-KS2-C004",
          "introduced": true,
          "importance": "core"
        },
        {
          "concept_id": "GE-KS3-C002",
          "introduced": false,
          "importance": "core"
        }
      ]
    },
    {
      "term_id": "VOC-GE-transportation",
      "term": "transportation",
      "definition": "The movement of eroded material by water, wind, ice, or gravity from one place to another.",
      "subject": "Geography",
      "word_class": "noun",
      "tier": 3,
      "etymology": "From Latin transportare",
      "example_usage": "Rivers transport sediment from the mountains to the sea.",
      "common_errors": "Confusing with the general meaning of transport (vehicles)",
      "related_everyday_word": "carrying",
      "concept_links": [
        {
          "concept_id": "GE-KS2-C003",
          "introduced": true,
          "importance": "core"
        }
      ]
    },
    {
      "term_id": "VOC-GE-tributary",
      "term": "tributary",
      "definition": "A smaller river or stream that flows into a larger river.",
      "subject": "Geography",
      "word_class": "noun",
      "tier": 3,
      "etymology": "From Latin tributarius, paying tribute",
      "example_usage": "The River Kennet is a tributary of the River Thames.",
      "common_errors": "",
      "related_everyday_word": "branch river",
      "concept_links": [
        {
          "concept_id": "GE-KS2-C003",
          "introduced": true,
          "importance": "core"
        }
      ]
    },
    {
      "term_id": "VOC-GE-tropic",
      "term": "tropic",
      "definition": "Either of the two lines of latitude at about 23.5 degrees north (Cancer) and south (Capricorn) of the equator.",
      "subject": "Geography",
      "word_class": "noun",
      "tier": 3,
      "etymology": "From Greek tropikos, of a turn",
      "example_usage": "The Tropic of Cancer marks the northern boundary of the tropical zone.",
      "common_errors": "",
      "related_everyday_word": "",
      "concept_links": [
        {
          "concept_id": "GE-KS2-C001",
          "introduced": true,
          "importance": "core"
        }
      ]
    },
    {
      "term_id": "VOC-GE-tropical",
      "term": "tropical",
      "definition": "Relating to the warm, wet region between the Tropic of Cancer and the Tropic of Capricorn.",
      "subject": "Geography",
      "word_class": "adjective",
      "tier": 3,
      "etymology": "From Greek tropikos",
      "example_usage": "Tropical climates are hot and humid with heavy rainfall.",
      "common_errors": "",
      "related_everyday_word": "hot and wet",
      "concept_links": [
        {
          "concept_id": "GE-KS2-C002",
          "introduced": true,
          "importance": "core"
        },
        {
          "concept_id": "GE-KS3-C005",
          "introduced": false,
          "importance": "core"
        }
      ]
    },
    {
      "term_id": "VOC-GE-tundra",
      "term": "tundra",
      "definition": "A cold, treeless biome found in polar regions with frozen ground and low-growing vegetation.",
      "subject": "Geography",
      "word_class": "noun",
      "tier": 3,
      "etymology": "From Russian tundra, from Sami tundar, treeless plain",
      "example_usage": "The tundra biome is too cold for trees to grow.",
      "common_errors": "",
      "related_everyday_word": "frozen plain",
      "concept_links": [
        {
          "concept_id": "GE-KS2-C002",
          "introduced": true,
          "importance": "core"
        },
        {
          "concept_id": "GE-KS3-C005",
          "introduced": false,
          "importance": "core"
        }
      ]
    },
    {
      "term_id": "VOC-GE-urbanisation",
      "term": "urbanisation",
      "definition": "The process by which an increasing proportion of a population moves to live in towns and cities.",
      "subject": "Geography",
      "word_class": "noun",
      "tier": 3,
      "etymology": "From Latin urbanus, of the city",
      "example_usage": "Urbanisation accelerated during the Industrial Revolution as people moved to factory towns.",
      "common_errors": "",
      "related_everyday_word": "city growth",
      "concept_links": [
        {
          "concept_id": "GE-KS2-C004",
          "introduced": true,
          "importance": "core"
        },
        {
          "concept_id": "GE-KS3-C004",
          "introduced": false,
          "importance": "core"
        },
        {
          "concept_id": "GE-KS4-C005",
          "introduced": false,
          "importance": "core"
        }
      ]
    },
    {
      "term_id": "VOC-GE-vegetation-belt",
      "term": "vegetation belt",
      "definition": "A zone of plant life that corresponds to a particular climate zone, running roughly parallel to the equator.",
      "subject": "Geography",
      "word_class": "phrase",
      "tier": 3,
      "etymology": "",
      "example_usage": "Vegetation belts range from tropical rainforest near the equator to tundra near the poles.",
      "common_errors": "",
      "related_everyday_word": "",
      "concept_links": [
        {
          "concept_id": "GE-KS2-C002",
          "introduced": true,
          "importance": "core"
        }
      ]
    },
    {
      "term_id": "VOC-GE-water-cycle",
      "term": "water cycle",
      "definition": "The continuous movement of water between the Earths surface and atmosphere through evaporation, condensation, and precipitation.",
      "subject": "Geography",
      "word_class": "phrase",
      "tier": 3,
      "etymology": "",
      "example_usage": "The water cycle explains how rain falls, flows into rivers, and eventually evaporates back into the atmosphere.",
      "common_errors": "Thinking the water cycle has a start and end; it is continuous",
      "related_everyday_word": "",
      "concept_links": [
        {
          "concept_id": "GE-KS2-C003",
          "introduced": true,
          "importance": "core"
        }
      ]
    }
  ]
}